{
	"num_threads": -1,
	"b_forceForwardSlashes": false,
	"configurations": {
		"DEBUG": {
			"bin": {
				"bin_name": "program.exc",
				"cc": "g++",
				"libs": [],
				"lflags": [],
				"lib_directories": [
					"libs"
				]
			},
			"rootPathReplace": [],
			"toolset": "GCC",
			"modules": {
				"MAIN": {
					"src": {
						"search": {
							"directories_recursive": [],
							"directories": [
								"src"
							],
							"filetypes": [
								"c",
								"cpp",
								"cxx"
							]
						},
						"src": []
					},
					"cc": "g++",
					"include_directories": {
						"include_directories_recursive": [
							"include_recursive"
						],
						"include_directories": [
							"include",
							"include/include2"
						]
					},
					"cflags": [],
					"pch": []
				}
			}
		}
	}
}